opendal-0.46.0.dist-info/METADATA
opendal-0.46.0.dist-info/WHEEL
opendal.libs/libgcc_s-e52197c3.so.1
opendal/__base.pyi
opendal/__init__.py
opendal/__init__.pyi
opendal/_opendal.cpython-310-aarch64-linux-gnu.so
opendal/exceptions.pyi
opendal/layers.pyi
opendal/py.typed
opendal-0.46.0.dist-info/RECORD
