Metadata-Version: 2.4
Name: opendal
Version: 0.46.0
Classifier: Programming Language :: Rust
Classifier: Programming Language :: Python :: Implementation :: CPython
Summary: Apache OpenDAL™ Python Binding
Home-Page: https://opendal.apache.org/
Author: Apache OpenDAL <dev@opendal.apache.org>
Author-email: Apache OpenDAL <dev@opendal.apache.org>
License: Apache-2.0
Requires-Python: >=3.10
Project-URL: Documentation, https://opendal.apache.org/docs/python/index.html
Project-URL: Homepage, https://opendal.apache.org/
Project-URL: Repository, https://github.com/apache/opendal
